pydatasci/__init__.py
pydatasci/aidb/__init__.py
pydatasci/data/.DS_Store
pydatasci/data/housing.csv
pydatasci/data/iris.tsv
pydatasci/data/iris_10x.tsv
pydatasci/data/iris_noHeaders.csv
pydatasci/data/sonar.csv
pydatasci/data/.ipynb_checkpoints/sonar-checkpoint.csv
pydatasci/examples/__init__.py
pydatasci-0.0.61.dist-info/LICENSE
pydatasci-0.0.61.dist-info/METADATA
pydatasci-0.0.61.dist-info/WHEEL
pydatasci-0.0.61.dist-info/top_level.txt
pydatasci-0.0.61.dist-info/RECORD
