Metadata-Version: 2.1
Name: pydatasci
Version: 0.0.61
Summary: End-to-end machine learning on your desktop or server.
Home-page: https://github.com/pydatasci-repo
Author: Layne Sadler
Author-email: layne@pydatasci.org
License: UNKNOWN
Platform: UNKNOWN
Classifier: Programming Language :: Python :: 3
Classifier: Natural Language :: English
Classifier: License :: OSI Approved :: GNU Affero General Public License v3
Classifier: Operating System :: OS Independent
Classifier: Development Status :: 1 - Planning
Classifier: Framework :: Jupyter
Classifier: Intended Audience :: Developers
Classifier: Topic :: Scientific/Engineering :: Artificial Intelligence
Requires-Dist: appdirs
Requires-Dist: keras
Requires-Dist: numpy
Requires-Dist: pandas
Requires-Dist: peewee
Requires-Dist: plotly
Requires-Dist: pyarrow
Requires-Dist: scikit-learn
Requires-Dist: tensorflow
Requires-Dist: tqdm
